flask_cognito_auth/.version
flask_cognito_auth/__init__.py
flask_cognito_auth/cognito_auth_manager.py
flask_cognito_auth/config.py
flask_cognito_auth/decorators.py
flask_cognito_auth-1.1.0.dist-info/LICENSE
flask_cognito_auth-1.1.0.dist-info/METADATA
flask_cognito_auth-1.1.0.dist-info/WHEEL
flask_cognito_auth-1.1.0.dist-info/top_level.txt
flask_cognito_auth-1.1.0.dist-info/RECORD
