Metadata-Version: 2.1
Name: flask-cognito-auth
Version: 1.1.0
Summary: Flask Cognito Authentication
Home-page: https://github.com/shrivastava-v-ankit/flask-cognito-auth
Author: Ankit Shrivastava
License: MIT
Project-URL: Source, https://github.com/shrivastava-v-ankit/flask-cognito-auth/
Project-URL: Tracker, https://github.com/shrivastava-v-ankit/flask-cognito-auth/issues
Keywords: flask,amazon cognito,json web token,authentication,autorization,oauth2,saml
Platform: any
Classifier: Development Status :: 5 - Production/Stable
Classifier: Environment :: Web Environment
Classifier: Framework :: Flask
Classifier: Intended Audience :: Developers
Classifier: Natural Language :: English
Classifier: License :: OSI Approved :: MIT License
Classifier: Operating System :: OS Independent
Classifier: Programming Language :: Python :: 3.4
Classifier: Programming Language :: Python :: 3.5
Classifier: Programming Language :: Python :: 3.6
Classifier: Programming Language :: Python :: 3.7
Classifier: Programming Language :: Python :: 3.8
Classifier: Topic :: Software Development :: Libraries :: Python Modules
Classifier: Topic :: Software Development :: Version Control :: Git
Requires-Python: >=3.4
Requires-Dist: Flask-WTF
Requires-Dist: requests
Requires-Dist: python-jose
